dlaas/__init__.py
dlaas-0.1.0.dist-info/WHEEL
dlaas-0.1.0.dist-info/METADATA
dlaas-0.1.0.dist-info/RECORD
