Metadata-Version: 2.1
Name: dlaas
Version: 0.1.0
Summary: Deep Learning as a service
Author: rcmalli
Author-email: refikcanmalli@gmail.com
Requires-Python: >=3.8,<4.0
Classifier: Programming Language :: Python :: 3
Classifier: Programming Language :: Python :: 3.8
Classifier: Programming Language :: Python :: 3.9
Classifier: Programming Language :: Python :: 3.10
